depup/__init__.py
depup/cli/__init__.py
depup/cli/main.py
depup/core/__init__.py
depup/core/environment_scanner.py
depup/core/exceptions.py
depup/core/models.py
depup/core/upgrade_executor.py
depup/core/version_scanner.py
depup/core/parsers/declaration_parser.py
depup/core/parsers/pipfile_lock_parser.py
depup/core/parsers/poetry_lock_parser.py
depup/utils/__init__.py
depup/utils/logging_config.py
depup/utils/render.py
depup/utils/report_utils.py
depup/utils/scan_utils.py
depup/utils/upgrade_planner.py
depup/utils/upgrade_utils.py
depup-0.9.0.dist-info/METADATA
depup-0.9.0.dist-info/WHEEL
depup-0.9.0.dist-info/entry_points.txt
depup-0.9.0.dist-info/licenses/LICENSE
depup-0.9.0.dist-info/RECORD
