Metadata-Version: 2.4
Name: depup
Version: 0.9.0
Summary: Dependency Upgrade Advisor: scan and safely upgrade Python project dependencies.
Author-email: Sai Saran Dammavalam <saran30702@gmail.com>
License-Expression: MIT
License-File: LICENSE
Keywords: cli,dependencies,python,semver,upgrade
Classifier: Environment :: Console
Classifier: Intended Audience :: Developers
Classifier: License :: OSI Approved :: MIT License
Classifier: Programming Language :: Python :: 3
Classifier: Programming Language :: Python :: 3 :: Only
Classifier: Topic :: Software Development :: Build Tools
Classifier: Topic :: Software Development :: Libraries :: Python Modules
Requires-Python: >=3.11
Requires-Dist: packaging==25.0
Requires-Dist: requests==2.32.5
Requires-Dist: rich==14.2.0
Requires-Dist: tomli-w==1.2.0
Requires-Dist: typer==0.20.0
Provides-Extra: dev
Requires-Dist: mypy; extra == 'dev'
Requires-Dist: pytest-cov; extra == 'dev'
Requires-Dist: pytest>=7.0; extra == 'dev'
Requires-Dist: ruff; extra == 'dev'
